antsibull_fileutils/__init__.py
antsibull_fileutils/copier.py
antsibull_fileutils/hashing.py
antsibull_fileutils/io.py
antsibull_fileutils/py.typed
antsibull_fileutils/tempfile.py
antsibull_fileutils/vcs.py
antsibull_fileutils/yaml.py
antsibull_fileutils-1.5.2.dist-info/METADATA
antsibull_fileutils-1.5.2.dist-info/WHEEL
antsibull_fileutils-1.5.2.dist-info/licenses/LICENSES/GPL-3.0-or-later.txt
antsibull_fileutils-1.5.2.dist-info/RECORD
